defs.v
`define B9600   9600
`define B19200  19200
`define CLOCK_50 50_000_000


`define GEN_CLK(clk, period) \
  initial begin \
    clk = 0; \
    forever begin \
      #period  clk = ~clk; \
    end \
  end

uart_tx.v
`include "defs.v"


module uart_tx
(
  input[7:0] data_i,
  input wr_i,
  input clk_i, rst_n_i,
  output TxD_o, TX_busy_o
);

reg[9:0] tx_r;
reg[3:0] tx_cnter;
reg[3:0] state, next;

wire tx_load = (state == ST_WRITE);
wire tx_shift = (state == ST_SEND);

always @ (posedge clk_i, negedge rst_n_i)
  if (~rst_n_i) begin
    tx_r <= 10'h200;
    tx_cnter <= 'b0;
  end
  else if (tx_load) begin
    tx_r <= {1'b0, data_i, 1'b1};
    tx_cnter <= 'b0;
  end 
  else if (tx_shift) begin
    tx_r <= {tx_r[8:0], 1'b1};
    tx_cnter <= tx_cnter + 'b1;
  end


parameter[3:0]  ST_IDLE   = 4'b0001,
                ST_DONE   = 4'b0010,
                ST_WRITE  = 4'b0100,
                ST_SEND   = 4'b1000;

always @(negedge clk_i)
  if (~rst_n_i) state <= ST_IDLE;
  else          state <= next;

always @* begin
  next = state;
  case (state)
    ST_IDLE: if (wr_i)  next = ST_WRITE;
    
    ST_WRITE: next = ST_SEND;

    ST_SEND: if (tx_cnter == 'd9) next = ST_DONE;
    
    ST_DONE: if (wr_i) next = ST_WRITE;
  endcase
end



assign TX_busy_o = (state == ST_SEND);
assign TxD_o = tx_r[9];

endmodule

uart_rx.v
`include "defs.v"

module uart_rx 
(
  input clk_i, rst_n_i, RxD_i,
  output [7:0] data_o,
  output RX_ack_o, RX_empty_o
);

/**********************************/
reg [8:0] rx_r;

/**********************************/
reg[4:0] state, next;
parameter[4:0]  ST_IDLE    		  = 5'b00001,
                ST_BIT2BIT    	= 5'b00010,
                ST_SAMPLE 			= 5'b00100,
                ST_SAMPLE_DONE 	= 5'b01000,
                ST_BIT2BIT_DONE = 5'b10000;

/**********************************/

always @(negedge clk_i, negedge rst_n_i) begin
  if (~rst_n_i)         state <= ST_IDLE;
  else                  state <= next;
end

`define FRAME_END (data_cnter_r == 'd10)

always @* begin
  next = state;
  case (state)
    ST_IDLE:  if (~RxD_i) next = ST_BIT2BIT;

    ST_SAMPLE_DONE: if (`FRAME_END)  next = ST_BIT2BIT_DONE; 
                    else             next = ST_SAMPLE;

    ST_BIT2BIT_DONE: if (~RxD_i) next = ST_SAMPLE; 
								     else        next = ST_IDLE;


    ST_SAMPLE: 	if (`FRAME_END)                   next = ST_BIT2BIT_DONE; 
						     else if (sample_cnter_r == 'hf)  next = ST_SAMPLE_DONE;

    ST_BIT2BIT:	if (sample_cnter_r == 'd6 && ~RxD_i) 	next = ST_SAMPLE_DONE; 
						     else if (RxD_i)            				  next = ST_BIT2BIT_DONE;

    default:  next = ST_IDLE;
  endcase
end


reg [3:0] sample_cnter_r; // 16 samples
reg [3:0] data_cnter_r;
reg [2:0] delay_cnter_r;


wire sample_cnter_rst = (state == ST_IDLE || state == ST_BIT2BIT_DONE || state == ST_SAMPLE_DONE);
wire sample_cnter_inc = (state == ST_SAMPLE || state == ST_BIT2BIT);

wire data_cnter_rst = (state == ST_IDLE || state == ST_BIT2BIT_DONE);
wire data_cnter_inc = (state == ST_SAMPLE_DONE);

//wire delay_cnter_inc = (state == ST_START);
//wire delay_cnter_rst = (state == ST_IDLE || state == ST_DONE);

wire rx_rst = (state == ST_BIT2BIT);
wire rx_shift = (state == ST_SAMPLE_DONE); //|| sample_cnter_r == 'd1));

always @ (posedge clk_i)
  if (rx_rst)         rx_r <= 'b0;
  else if (rx_shift)  rx_r <= {rx_r[7:0], RxD_i};

//always @ (posedge clk_i)
//  if (delay_cnter_rst)      delay_cnter_r <= 'b0;
//  else if (delay_cnter_inc) delay_cnter_r <= delay_cnter_r + 'b1;

always @ (posedge clk_i) 
  if (data_cnter_rst)       data_cnter_r <= 'b0;
  else if (data_cnter_inc)  data_cnter_r <= data_cnter_r + 'b1;

always @ (posedge clk_i)
  if (sample_cnter_rst)      sample_cnter_r <= 'b0;
  else if (sample_cnter_inc) sample_cnter_r <= sample_cnter_r + 'b1;



    // if rx == 0 start sampling
    // count up to 7, the middle position of the start bit
    // reset the counter
    // count up to 15, up to the middle position of the first data bit
    // repeat N-1 times (N=8)
    // repeat once more for the parity bit
    // repat once more for the stop bit
    //

assign RX_ack_o = (state == ST_BIT2BIT_DONE);
assign data_o 	= rx_r[8:1];
assign RX_empty_o = ~|data_o;

endmodule

baud_gen.v
`include "defs.v"

module baud_gen
(
  input clk_i, rst_n_i,
  // set baud rate 
  //
  input[WIDTH-1:0] baud_modulo_i, // sys_clk_i / baud_rate
  output baud_clk_o
);
//localparam WIDTH = $clog2(`B19200);
localparam WIDTH = 32;

/**************************************/

// generate clock
// RX/TX clk = sys_clk / baudrate
reg [WIDTH-1:0] baud_cnter_r;
reg baud_clk;
//always @ (posedge sys_clk_i, negedge rst_n_i) begin
always @ (posedge clk_i) begin
  if (~rst_n_i)  begin
    baud_cnter_r <= 0;
    baud_clk <= 0;
  end else 
  if (baud_cnter_r == baud_modulo_i) begin
    baud_cnter_r <= 0;
    baud_clk <= ~baud_clk;
  end
  else
    baud_cnter_r <= baud_cnter_r + 1;
end
// outputs
assign baud_clk_o = baud_clk;

endmodule

uart_tb.v
`include "defs.v"
`include "timescale.v"

module uart_tb();

reg clk, rst;
reg [7:0] tx_data;
reg tx_wr;

wire rx_ack, rx_empty, tx_busy;
wire TxD;
wire tx_clk, rx_clk;

baud_gen tx_gen(
  .clk_i(clk),
  .rst_n_i(rst),
  .baud_modulo_i(32'd31),
  .baud_clk_o(tx_clk)
);

baud_gen rx_gen(
  .clk_i(clk),
  .rst_n_i(rst),
  .baud_modulo_i(32'd01),
  .baud_clk_o(rx_clk)
);


uart_rx urx(
  .clk_i(rx_clk),
  .rst_n_i(rst),
  .RxD_i(TxD),
  .RX_ack_o(rx_ack),
  .RX_empty_o(rx_empty)
);

uart_tx utx(
  .clk_i(tx_clk),
  .rst_n_i(rst),
  .TxD_o(TxD),
  .TX_busy_o(tx_busy),
  .data_i(tx_data),
  .wr_i(tx_wr)
);


`GEN_CLK(clk, 20)

initial begin
  $dumpfile("uart.vcd");
  $dumpvars(0, uart_tb); 
end



initial begin
  rst = 1;
  #50;
  rst = 0;
  #100;
  rst = 1;

  tx_data = 8'b1010_1010;
  tx_wr = 1;
  //#3000;
  //tx_wr = 0;

  #60000;
  $finish;
end


endmodule

uart.vcd
$date
	Tue Nov  7 10:07:26 2017
$end
$version
	Icarus Verilog
$end
$timescale
	1ps
$end
$scope module uart_tb $end
$var wire 1 ! tx_clk $end
$var wire 1 " tx_busy $end
$var wire 1 # rx_empty $end
$var wire 1 $ rx_clk $end
$var wire 1 % rx_ack $end
$var wire 1 & TxD $end
$var reg 1 ' clk $end
$var reg 1 ( rst $end
$var reg 8 ) tx_data [7:0] $end
$var reg 1 * tx_wr $end
$scope module rx_gen $end
$var wire 1 $ baud_clk_o $end
$var wire 32 + baud_modulo_i [31:0] $end
$var wire 1 ' clk_i $end
$var wire 1 ( rst_n_i $end
$var reg 1 , baud_clk $end
$var reg 32 - baud_cnter_r [31:0] $end
$upscope $end
$scope module tx_gen $end
$var wire 1 ! baud_clk_o $end
$var wire 32 . baud_modulo_i [31:0] $end
$var wire 1 ' clk_i $end
$var wire 1 ( rst_n_i $end
$var reg 1 / baud_clk $end
$var reg 32 0 baud_cnter_r [31:0] $end
$upscope $end
$scope module urx $end
$var wire 1 $ clk_i $end
$var wire 1 1 data_cnter_rst $end
$var wire 1 ( rst_n_i $end
$var wire 1 2 sample_cnter_inc $end
$var wire 1 3 sample_cnter_rst $end
$var wire 1 4 rx_shift $end
$var wire 1 5 rx_rst $end
$var wire 8 6 data_o [7:0] $end
$var wire 1 7 data_cnter_inc $end
$var wire 1 & RxD_i $end
$var wire 1 # RX_empty_o $end
$var wire 1 % RX_ack_o $end
$var reg 4 8 data_cnter_r [3:0] $end
$var reg 5 9 next [4:0] $end
$var reg 9 : rx_r [8:0] $end
$var reg 4 ; sample_cnter_r [3:0] $end
$var reg 5 < state [4:0] $end
$upscope $end
$scope module utx $end
$var wire 1 ! clk_i $end
$var wire 8 = data_i [7:0] $end
$var wire 1 ( rst_n_i $end
$var wire 1 * wr_i $end
$var wire 1 > tx_shift $end
$var wire 1 ? tx_load $end
$var wire 1 & TxD_o $end
$var wire 1 " TX_busy_o $end
$var reg 4 @ next [3:0] $end
$var reg 4 A state [3:0] $end
$var reg 4 B tx_cnter [3:0] $end
$var reg 10 C tx_r [9:0] $end
$upscope $end
$upscope $end
$enddefinitions $end
#0
$dumpvars
bx C
bx B
bx A
bx @
x?
x>
bx =
bx <
bx ;
bx :
bx 9
bx 8
x7
bx 6
x5
x4
x3
x2
x1
bx 0
x/
b11111 .
bx -
x,
b1 +
x*
bx )
1(
0'
x&
x%
x$
x#
x"
x!
$end
#20000
1'
#40000
0'
#50000
13
b1 9
02
11
1&
07
05
04
0%
b1 <
b0 B
b1000000000 C
0(
#60000
b1 @
0?
0>
0"
b1 A
0$
0,
b0 -
0!
0/
b0 0
1'
#80000
0'
#100000
1'
#120000
0'
#140000
1'
#150000
b100 @
1*
b10101010 )
b10101010 =
1(
#160000
0'
#180000
b1 0
b1 -
1'
#200000
0'
#220000
b0 8
b0 ;
1$
1,
b0 -
b10 0
1'
#240000
0'
#260000
b11 0
b1 -
1'
#280000
0'
#300000
0$
0,
b0 -
b100 0
1'
#320000
0'
#340000
b101 0
b1 -
1'
#360000
0'
#380000
1$
1,
b0 -
b110 0
1'
#400000
0'
#420000
b111 0
b1 -
1'
#440000
0'
#460000
0$
0,
b0 -
b1000 0
1'
#480000
0'
#500000
b1001 0
b1 -
1'
#520000
0'
#540000
1$
1,
b0 -
b1010 0
1'
#560000
0'
#580000
b1011 0
b1 -
1'
#600000
0'
#620000
0$
0,
b0 -
b1100 0
1'
#640000
0'
#660000
b1101 0
b1 -
1'
#680000
0'
#700000
1$
1,
b0 -
b1110 0
1'
#720000
0'
#740000
b1111 0
b1 -
1'
#760000
0'
#780000
0$
0,
b0 -
b10000 0
1'
#800000
0'
#820000
b10001 0
b1 -
1'
#840000
0'
#860000
1$
1,
b0 -
b10010 0
1'
#880000
0'
#900000
b10011 0
b1 -
1'
#920000
0'
#940000
0$
0,
b0 -
b10100 0
1'
#960000
0'
#980000
b10101 0
b1 -
1'
#1000000
0'
#1020000
1$
1,
b0 -
b10110 0
1'
#1040000
0'
#1060000
b10111 0
b1 -
1'
#1080000
0'
#1100000
0$
0,
b0 -
b11000 0
1'
#1120000
0'
#1140000
b11001 0
b1 -
1'
#1160000
0'
#1180000
1$
1,
b0 -
b11010 0
1'
#1200000
0'
#1220000
b11011 0
b1 -
1'
#1240000
0'
#1260000
0$
0,
b0 -
b11100 0
1'
#1280000
0'
#1300000
b11101 0
b1 -
1'
#1320000
0'
#1340000
1$
1,
b0 -
b11110 0
1'
#1360000
0'
#1380000
b11111 0
b1 -
1'
#1400000
0'
#1420000
0$
0,
b0 -
1!
1/
b0 0
1'
#1440000
0'
#1460000
b1 0
b1 -
1'
#1480000
0'
#1500000
1$
1,
b0 -
b10 0
1'
#1520000
0'
#1540000
b11 0
b1 -
1'
#1560000
0'
#1580000
0$
0,
b0 -
b100 0
1'
#1600000
0'
#1620000
b101 0
b1 -
1'
#1640000
0'
#1660000
1$
1,
b0 -
b110 0
1'
#1680000
0'
#1700000
b111 0
b1 -
1'
#1720000
0'
#1740000
0$
0,
b0 -
b1000 0
1'
#1760000
0'
#1780000
b1001 0
b1 -
1'
#1800000
0'
#1820000
1$
1,
b0 -
b1010 0
1'
#1840000
0'
#1860000
b1011 0
b1 -
1'
#1880000
0'
#1900000
0$
0,
b0 -
b1100 0
1'
#1920000
0'
#1940000
b1101 0
b1 -
1'
#1960000
0'
#1980000
1$
1,
b0 -
b1110 0
1'
#2000000
0'
#2020000
b1111 0
b1 -
1'
#2040000
0'
#2060000
0$
0,
b0 -
b10000 0
1'
#2080000
0'
#2100000
b10001 0
b1 -
1'
#2120000
0'
#2140000
1$
1,
b0 -
b10010 0
1'
#2160000
0'
#2180000
b10011 0
b1 -
1'
#2200000
0'
#2220000
0$
0,
b0 -
b10100 0
1'
#2240000
0'
#2260000
b10101 0
b1 -
1'
#2280000
0'
#2300000
1$
1,
b0 -
b10110 0
1'
#2320000
0'
#2340000
b10111 0
b1 -
1'
#2360000
0'
#2380000
0$
0,
b0 -
b11000 0
1'
#2400000
0'
#2420000
b11001 0
b1 -
1'
#2440000
0'
#2460000
1$
1,
b0 -
b11010 0
1'
#2480000
0'
#2500000
b11011 0
b1 -
1'
#2520000
0'
#2540000
0$
0,
b0 -
b11100 0
1'
#2560000
0'
#2580000
b11101 0
b1 -
1'
#2600000
0'
#2620000
1$
1,
b0 -
b11110 0
1'
#2640000
0'
#2660000
b11111 0
b1 -
1'
#2680000
0'
#2700000
b1000 @
1?
b100 A
0$
0,
b0 -
0!
0/
b0 0
1'
#2720000
0'
#2740000
b1 0
b1 -
1'
#2760000
0'
#2780000
1$
1,
b0 -
b10 0
1'
#2800000
0'
#2820000
b11 0
b1 -
1'
#2840000
0'
#2860000
0$
0,
b0 -
b100 0
1'
#2880000
0'
#2900000
b101 0
b1 -
1'
#2920000
0'
#2940000
1$
1,
b0 -
b110 0
1'
#2960000
0'
#2980000
b111 0
b1 -
1'
#3000000
0'
#3020000
0$
0,
b0 -
b1000 0
1'
#3040000
0'
#3060000
b1001 0
b1 -
1'
#3080000
0'
#3100000
1$
1,
b0 -
b1010 0
1'
#3120000
0'
#3140000
b1011 0
b1 -
1'
#3160000
0'
#3180000
0$
0,
b0 -
b1100 0
1'
#3200000
0'
#3220000
b1101 0
b1 -
1'
#3240000
0'
#3260000
1$
1,
b0 -
b1110 0
1'
#3280000
0'
#3300000
b1111 0
b1 -
1'
#3320000
0'
#3340000
0$
0,
b0 -
b10000 0
1'
#3360000
0'
#3380000
b10001 0
b1 -
1'
#3400000
0'
#3420000
1$
1,
b0 -
b10010 0
1'
#3440000
0'
#3460000
b10011 0
b1 -
1'
#3480000
0'
#3500000
0$
0,
b0 -
b10100 0
1'
#3520000
0'
#3540000
b10101 0
b1 -
1'
#3560000
0'
#3580000
1$
1,
b0 -
b10110 0
1'
#3600000
0'
#3620000
b10111 0
b1 -
1'
#3640000
0'
#3660000
0$
0,
b0 -
b11000 0
1'
#3680000
0'
#3700000
b11001 0
b1 -
1'
#3720000
0'
#3740000
1$
1,
b0 -
b11010 0
1'
#3760000
0'
#3780000
b11011 0
b1 -
1'
#3800000
0'
#3820000
0$
0,
b0 -
b11100 0
1'
#3840000
0'
#3860000
b11101 0
b1 -
1'
#3880000
0'
#3900000
1$
1,
b0 -
b11110 0
1'
#3920000
0'
#3940000
b11111 0
b1 -
1'
#3960000
0'
#3980000
b10 9
0&
b101010101 C
0$
0,
b0 -
1!
1/
b0 0
1'
#4000000
0'
#4020000
b1 0
b1 -
1'
#4040000
0'
#4060000
1$
1,
b0 -
b10 0
1'
#4080000
0'
#4100000
b11 0
b1 -
1'
#4120000
0'
#4140000
03
12
01
15
b10 <
0$
0,
b0 -
b100 0
1'
#4160000
0'
#4180000
b101 0
b1 -
1'
#4200000
0'
#4220000
1#
b0 6
b1 ;
b0 :
1$
1,
b0 -
b110 0
1'
#4240000
0'
#4260000
b111 0
b1 -
1'
#4280000
0'
#4300000
0$
0,
b0 -
b1000 0
1'
#4320000
0'
#4340000
b1001 0
b1 -
1'
#4360000
0'
#4380000
b10 ;
1$
1,
b0 -
b1010 0
1'
#4400000
0'
#4420000
b1011 0
b1 -
1'
#4440000
0'
#4460000
0$
0,
b0 -
b1100 0
1'
#4480000
0'
#4500000
b1101 0
b1 -
1'
#4520000
0'
#4540000
b11 ;
1$
1,
b0 -
b1110 0
1'
#4560000
0'
#4580000
b1111 0
b1 -
1'
#4600000
0'
#4620000
0$
0,
b0 -
b10000 0
1'
#4640000
0'
#4660000
b10001 0
b1 -
1'
#4680000
0'
#4700000
b100 ;
1$
1,
b0 -
b10010 0
1'
#4720000
0'
#4740000
b10011 0
b1 -
1'
#4760000
0'
#4780000
0$
0,
b0 -
b10100 0
1'
#4800000
0'
#4820000
b10101 0
b1 -
1'
#4840000
0'
#4860000
b101 ;
1$
1,
b0 -
b10110 0
1'
#4880000
0'
#4900000
b10111 0
b1 -
1'
#4920000
0'
#4940000
0$
0,
b0 -
b11000 0
1'
#4960000
0'
#4980000
b11001 0
b1 -
1'
#5000000
0'
#5020000
b1000 9
b110 ;
1$
1,
b0 -
b11010 0
1'
#5040000
0'
#5060000
b11011 0
b1 -
1'
#5080000
0'
#5100000
b100 9
13
02
17
05
14
b1000 <
0$
0,
b0 -
b11100 0
1'
#5120000
0'
#5140000
b11101 0
b1 -
1'
#5160000
0'
#5180000
b100 9
b0 ;
b1 8
1$
1,
b0 -
b11110 0
1'
#5200000
0'
#5220000
b11111 0
b1 -
1'
#5240000
0'
#5260000
03
12
07
04
b100 <
0?
1>
1"
b1000 A
0$
0,
b0 -
0!
0/
b0 0
1'
#5280000
0'
#5300000
b1 0
b1 -
1'
#5320000
0'
#5340000
b1 ;
1$
1,
b0 -
b10 0
1'
#5360000
0'
#5380000
b11 0
b1 -
1'
#5400000
0'
#5420000
0$
0,
b0 -
b100 0
1'
#5440000
0'
#5460000
b101 0
b1 -
1'
#5480000
0'
#5500000
b10 ;
1$
1,
b0 -
b110 0
1'
#5520000
0'
#5540000
b111 0
b1 -
1'
#5560000
0'
#5580000
0$
0,
b0 -
b1000 0
1'
#5600000
0'
#5620000
b1001 0
b1 -
1'
#5640000
0'
#5660000
b11 ;
1$
1,
b0 -
b1010 0
1'
#5680000
0'
#5700000
b1011 0
b1 -
1'
#5720000
0'
#5740000
0$
0,
b0 -
b1100 0
1'
#5760000
0'
#5780000
b1101 0
b1 -
1'
#5800000
0'
#5820000
b100 ;
1$
1,
b0 -
b1110 0
1'
#5840000
0'
#5860000
b1111 0
b1 -
1'
#5880000
0'
#5900000
0$
0,
b0 -
b10000 0
1'
#5920000
0'
#5940000
b10001 0
b1 -
1'
#5960000
0'
#5980000
b101 ;
1$
1,
b0 -
b10010 0
1'
#6000000
0'
#6020000
b10011 0
b1 -
1'
#6040000
0'
#6060000
0$
0,
b0 -
b10100 0
1'
#6080000
0'
#6100000
b10101 0
b1 -
1'
#6120000
0'
#6140000
b110 ;
1$
1,
b0 -
b10110 0
1'
#6160000
0'
#6180000
b10111 0
b1 -
1'
#6200000
0'
#6220000
0$
0,
b0 -
b11000 0
1'
#6240000
0'
#6260000
b11001 0
b1 -
1'
#6280000
0'
#6300000
b111 ;
1$
1,
b0 -
b11010 0
1'
#6320000
0'
#6340000
b11011 0
b1 -
1'
#6360000
0'
#6380000
0$
0,
b0 -
b11100 0
1'
#6400000
0'
#6420000
b11101 0
b1 -
1'
#6440000
0'
#6460000
b1000 ;
1$
1,
b0 -
b11110 0
1'
#6480000
0'
#6500000
b11111 0
b1 -
1'
#6520000
0'
#6540000
1&
b1 B
b1010101011 C
0$
0,
b0 -
1!
1/
b0 0
1'
#6560000
0'
#6580000
b1 0
b1 -
1'
#6600000
0'
#6620000
b1001 ;
1$
1,
b0 -
b10 0
1'
#6640000
0'
#6660000
b11 0
b1 -
1'
#6680000
0'
#6700000
0$
0,
b0 -
b100 0
1'
#6720000
0'
#6740000
b101 0
b1 -
1'
#6760000
0'
#6780000
b1010 ;
1$
1,
b0 -
b110 0
1'
#6800000
0'
#6820000
b111 0
b1 -
1'
#6840000
0'
#6860000
0$
0,
b0 -
b1000 0
1'
#6880000
0'
#6900000
b1001 0
b1 -
1'
#6920000
0'
#6940000
b1011 ;
1$
1,
b0 -
b1010 0
1'
#6960000
0'
#6980000
b1011 0
b1 -
1'
#7000000
0'
#7020000
0$
0,
b0 -
b1100 0
1'
#7040000
0'
#7060000
b1101 0
b1 -
1'
#7080000
0'
#7100000
b1100 ;
1$
1,
b0 -
b1110 0
1'
#7120000
0'
#7140000
b1111 0
b1 -
1'
#7160000
0'
#7180000
0$
0,
b0 -
b10000 0
1'
#7200000
0'
#7220000
b10001 0
b1 -
1'
#7240000
0'
#7260000
b1101 ;
1$
1,
b0 -
b10010 0
1'
#7280000
0'
#7300000
b10011 0
b1 -
1'
#7320000
0'
#7340000
0$
0,
b0 -
b10100 0
1'
#7360000
0'
#7380000
b10101 0
b1 -
1'
#7400000
0'
#7420000
b1110 ;
1$
1,
b0 -
b10110 0
1'
#7440000
0'
#7460000
b10111 0
b1 -
1'
#7480000
0'
#7500000
0$
0,
b0 -
b11000 0
1'
#7520000
0'
#7540000
b11001 0
b1 -
1'
#7560000
0'
#7580000
b1000 9
b1111 ;
1$
1,
b0 -
b11010 0
1'
#7600000
0'
#7620000
b11011 0
b1 -
1'
#7640000
0'
#7660000
b100 9
13
02
17
14
b1000 <
0$
0,
b0 -
b11100 0
1'
#7680000
0'
#7700000
b11101 0
b1 -
1'
#7720000
0'
#7740000
b100 9
b0 ;
b10 8
b1 :
1$
1,
b0 -
b11110 0
1'
#7760000
0'
#7780000
b11111 0
b1 -
1'
#7800000
0'
#7820000
03
12
07
04
b100 <
0$
0,
b0 -
0!
0/
b0 0
1'
#7840000
0'
#7860000
b1 0
b1 -
1'
#7880000
0'
#7900000
b1 ;
1$
1,
b0 -
b10 0
1'
#7920000
0'
#7940000
b11 0
b1 -
1'
#7960000
0'
#7980000
0$
0,
b0 -
b100 0
1'
#8000000
0'
#8020000
b101 0
b1 -
1'
#8040000
0'
#8060000
b10 ;
1$
1,
b0 -
b110 0
1'
#8080000
0'
#8100000
b111 0
b1 -
1'
#8120000
0'
#8140000
0$
0,
b0 -
b1000 0
1'
#8160000
0'
#8180000
b1001 0
b1 -
1'
#8200000
0'
#8220000
b11 ;
1$
1,
b0 -
b1010 0
1'
#8240000
0'
#8260000
b1011 0
b1 -
1'
#8280000
0'
#8300000
0$
0,
b0 -
b1100 0
1'
#8320000
0'
#8340000
b1101 0
b1 -
1'
#8360000
0'
#8380000
b100 ;
1$
1,
b0 -
b1110 0
1'
#8400000
0'
#8420000
b1111 0
b1 -
1'
#8440000
0'
#8460000
0$
0,
b0 -
b10000 0
1'
#8480000
0'
#8500000
b10001 0
b1 -
1'
#8520000
0'
#8540000
b101 ;
1$
1,
b0 -
b10010 0
1'
#8560000
0'
#8580000
b10011 0
b1 -
1'
#8600000
0'
#8620000
0$
0,
b0 -
b10100 0
1'
#8640000
0'
#8660000
b10101 0
b1 -
1'
#8680000
0'
#8700000
b110 ;
1$
1,
b0 -
b10110 0
1'
#8720000
0'
#8740000
b10111 0
b1 -
1'
#8760000
0'
#8780000
0$
0,
b0 -
b11000 0
1'
#8800000
0'
#8820000
b11001 0
b1 -
1'
#8840000
0'
#8860000
b111 ;
1$
1,
b0 -
b11010 0
1'
#8880000
0'
#8900000
b11011 0
b1 -
1'
#8920000
0'
#8940000
0$
0,
b0 -
b11100 0
1'
#8960000
0'
#8980000
b11101 0
b1 -
1'
#9000000
0'
#9020000
b1000 ;
1$
1,
b0 -
b11110 0
1'
#9040000
0'
#9060000
b11111 0
b1 -
1'
#9080000
0'
#9100000
0&
b10 B
b101010111 C
0$
0,
b0 -
1!
1/
b0 0
1'
#9120000
0'
#9140000
b1 0
b1 -
1'
#9160000
0'
#9180000
b1001 ;
1$
1,
b0 -
b10 0
1'
#9200000
0'
#9220000
b11 0
b1 -
1'
#9240000
0'
#9260000
0$
0,
b0 -
b100 0
1'
#9280000
0'
#9300000
b101 0
b1 -
1'
#9320000
0'
#9340000
b1010 ;
1$
1,
b0 -
b110 0
1'
#9360000
0'
#9380000
b111 0
b1 -
1'
#9400000
0'
#9420000
0$
0,
b0 -
b1000 0
1'
#9440000
0'
#9460000
b1001 0
b1 -
1'
#9480000
0'
#9500000
b1011 ;
1$
1,
b0 -
b1010 0
1'
#9520000
0'
#9540000
b1011 0
b1 -
1'
#9560000
0'
#9580000
0$
0,
b0 -
b1100 0
1'
#9600000
0'
#9620000
b1101 0
b1 -
1'
#9640000
0'
#9660000
b1100 ;
1$
1,
b0 -
b1110 0
1'
#9680000
0'
#9700000
b1111 0
b1 -
1'
#9720000
0'
#9740000
0$
0,
b0 -
b10000 0
1'
#9760000
0'
#9780000
b10001 0
b1 -
1'
#9800000
0'
#9820000
b1101 ;
1$
1,
b0 -
b10010 0
1'
#9840000
0'
#9860000
b10011 0
b1 -
1'
#9880000
0'
#9900000
0$
0,
b0 -
b10100 0
1'
#9920000
0'
#9940000
b10101 0
b1 -
1'
#9960000
0'
#9980000
b1110 ;
1$
1,
b0 -
b10110 0
1'
#10000000
0'
#10020000
b10111 0
b1 -
1'
#10040000
0'
#10060000
0$
0,
b0 -
b11000 0
1'
#10080000
0'
#10100000
b11001 0
b1 -
1'
#10120000
0'
#10140000
b1000 9
b1111 ;
1$
1,
b0 -
b11010 0
1'
#10160000
0'
#10180000
b11011 0
b1 -
1'
#10200000
0'
#10220000
b100 9
13
02
17
14
b1000 <
0$
0,
b0 -
b11100 0
1'
#10240000
0'
#10260000
b11101 0
b1 -
1'
#10280000
0'
#10300000
b100 9
0#
b1 6
b0 ;
b11 8
b10 :
1$
1,
b0 -
b11110 0
1'
#10320000
0'
#10340000
b11111 0
b1 -
1'
#10360000
0'
#10380000
03
12
07
04
b100 <
0$
0,
b0 -
0!
0/
b0 0
1'
#10400000
0'
#10420000
b1 0
b1 -
1'
#10440000
0'
#10460000
b1 ;
1$
1,
b0 -
b10 0
1'
#10480000
0'
#10500000
b11 0
b1 -
1'
#10520000
0'
#10540000
0$
0,
b0 -
b100 0
1'
#10560000
0'
#10580000
b101 0
b1 -
1'
#10600000
0'
#10620000
b10 ;
1$
1,
b0 -
b110 0
1'
#10640000
0'
#10660000
b111 0
b1 -
1'
#10680000
0'
#10700000
0$
0,
b0 -
b1000 0
1'
#10720000
0'
#10740000
b1001 0
b1 -
1'
#10760000
0'
#10780000
b11 ;
1$
1,
b0 -
b1010 0
1'
#10800000
0'
#10820000
b1011 0
b1 -
1'
#10840000
0'
#10860000
0$
0,
b0 -
b1100 0
1'
#10880000
0'
#10900000
b1101 0
b1 -
1'
#10920000
0'
#10940000
b100 ;
1$
1,
b0 -
b1110 0
1'
#10960000
0'
#10980000
b1111 0
b1 -
1'
#11000000
0'
#11020000
0$
0,
b0 -
b10000 0
1'
#11040000
0'
#11060000
b10001 0
b1 -
1'
#11080000
0'
#11100000
b101 ;
1$
1,
b0 -
b10010 0
1'
#11120000
0'
#11140000
b10011 0
b1 -
1'
#11160000
0'
#11180000
0$
0,
b0 -
b10100 0
1'
#11200000
0'
#11220000
b10101 0
b1 -
1'
#11240000
0'
#11260000
b110 ;
1$
1,
b0 -
b10110 0
1'
#11280000
0'
#11300000
b10111 0
b1 -
1'
#11320000
0'
#11340000
0$
0,
b0 -
b11000 0
1'
#11360000
0'
#11380000
b11001 0
b1 -
1'
#11400000
0'
#11420000
b111 ;
1$
1,
b0 -
b11010 0
1'
#11440000
0'
#11460000
b11011 0
b1 -
1'
#11480000
0'
#11500000
0$
0,
b0 -
b11100 0
1'
#11520000
0'
#11540000
b11101 0
b1 -
1'
#11560000
0'
#11580000
b1000 ;
1$
1,
b0 -
b11110 0
1'
#11600000
0'
#11620000
b11111 0
b1 -
1'
#11640000
0'
#11660000
1&
b11 B
b1010101111 C
0$
0,
b0 -
1!
1/
b0 0
1'
#11680000
0'
#11700000
b1 0
b1 -
1'
#11720000
0'
#11740000
b1001 ;
1$
1,
b0 -
b10 0
1'
#11760000
0'
#11780000
b11 0
b1 -
1'
#11800000
0'
#11820000
0$
0,
b0 -
b100 0
1'
#11840000
0'
#11860000
b101 0
b1 -
1'
#11880000
0'
#11900000
b1010 ;
1$
1,
b0 -
b110 0
1'
#11920000
0'
#11940000
b111 0
b1 -
1'
#11960000
0'
#11980000
0$
0,
b0 -
b1000 0
1'
#12000000
0'
#12020000
b1001 0
b1 -
1'
#12040000
0'
#12060000
b1011 ;
1$
1,
b0 -
b1010 0
1'
#12080000
0'
#12100000
b1011 0
b1 -
1'
#12120000
0'
#12140000
0$
0,
b0 -
b1100 0
1'
#12160000
0'
#12180000
b1101 0
b1 -
1'
#12200000
0'
#12220000
b1100 ;
1$
1,
b0 -
b1110 0
1'
#12240000
0'
#12260000
b1111 0
b1 -
1'
#12280000
0'
#12300000
0$
0,
b0 -
b10000 0
1'
#12320000
0'
#12340000
b10001 0
b1 -
1'
#12360000
0'
#12380000
b1101 ;
1$
1,
b0 -
b10010 0
1'
#12400000
0'
#12420000
b10011 0
b1 -
1'
#12440000
0'
#12460000
0$
0,
b0 -
b10100 0
1'
#12480000
0'
#12500000
b10101 0
b1 -
1'
#12520000
0'
#12540000
b1110 ;
1$
1,
b0 -
b10110 0
1'
#12560000
0'
#12580000
b10111 0
b1 -
1'
#12600000
0'
#12620000
0$
0,
b0 -
b11000 0
1'
#12640000
0'
#12660000
b11001 0
b1 -
1'
#12680000
0'
#12700000
b1000 9
b1111 ;
1$
1,
b0 -
b11010 0
1'
#12720000
0'
#12740000
b11011 0
b1 -
1'
#12760000
0'
#12780000
b100 9
13
02
17
14
b1000 <
0$
0,
b0 -
b11100 0
1'
#12800000
0'
#12820000
b11101 0
b1 -
1'
#12840000
0'
#12860000
b100 9
b10 6
b0 ;
b100 8
b101 :
1$
1,
b0 -
b11110 0
1'
#12880000
0'
#12900000
b11111 0
b1 -
1'
#12920000
0'
#12940000
03
12
07
04
b100 <
0$
0,
b0 -
0!
0/
b0 0
1'
#12960000
0'
#12980000
b1 0
b1 -
1'
#13000000
0'
#13020000
b1 ;
1$
1,
b0 -
b10 0
1'
#13040000
0'
#13060000
b11 0
b1 -
1'
